MANIFEST.in
README.md
setup.py
etc/func-inventory-notifier.conf
func/__init__.py
func/overlord/__init__.py
func/overlord/inventory_notifier.py
func_inventory_notifier.egg-info/PKG-INFO
func_inventory_notifier.egg-info/SOURCES.txt
func_inventory_notifier.egg-info/dependency_links.txt
func_inventory_notifier.egg-info/requires.txt
func_inventory_notifier.egg-info/top_level.txt
scripts/func-inventory-notifier