Metadata-Version: 1.0
Name: func-inventory-notifier
Version: 0.2.2
Summary: Send colorized HTML notifications of func-inventory
Home-page: http://github.com/ralphbean/func-inventory-notifier
Author: Ralph Bean
Author-email: ralph.bean@gmail.com
License: UNKNOWN
Platform: UNKNOWN
